odoo9_addon_account_invoice_pricelist-9.0.1.0.0-py2.7-nspkg.pth
odoo_addons/account_invoice_pricelist/__openerp__.py
odoo_addons/account_invoice_pricelist/__init__.py
odoo_addons/account_invoice_pricelist/README.rst
odoo_addons/account_invoice_pricelist/view/view.xml
odoo_addons/account_invoice_pricelist/l10n/fr.po
odoo_addons/account_invoice_pricelist/l10n/account_invoice_pricelist.pot
odoo_addons/account_invoice_pricelist/i18n/zh_CN.po
odoo_addons/account_invoice_pricelist/i18n/it.po
odoo_addons/account_invoice_pricelist/i18n/es.po
odoo_addons/account_invoice_pricelist/i18n/hr.po
odoo_addons/account_invoice_pricelist/i18n/sl.po
odoo_addons/account_invoice_pricelist/i18n/nl.po
odoo_addons/account_invoice_pricelist/i18n/de.po
odoo_addons/account_invoice_pricelist/i18n/fr.po
odoo_addons/account_invoice_pricelist/i18n/pt_BR.po
odoo_addons/account_invoice_pricelist/i18n/el_GR.po
odoo_addons/account_invoice_pricelist/model/account_invoice.py
odoo_addons/account_invoice_pricelist/model/__init__.py
odoo_addons/account_invoice_pricelist/model/account_invoice_line.py
odoo_addons/account_invoice_pricelist/tests/test_account_invoice_pricelist.py
odoo_addons/account_invoice_pricelist/tests/__init__.py
odoo_addons/account_invoice_pricelist/demo/res_groups.yml
odoo_addons/account_invoice_pricelist/static/src/description/screenshot_group_by.png
odoo_addons/account_invoice_pricelist/static/src/description/icon.png
odoo9_addon_account_invoice_pricelist-9.0.1.0.0.dist-info/top_level.txt
odoo9_addon_account_invoice_pricelist-9.0.1.0.0.dist-info/WHEEL
odoo9_addon_account_invoice_pricelist-9.0.1.0.0.dist-info/RECORD
odoo9_addon_account_invoice_pricelist-9.0.1.0.0.dist-info/metadata.json
odoo9_addon_account_invoice_pricelist-9.0.1.0.0.dist-info/DESCRIPTION.rst
odoo9_addon_account_invoice_pricelist-9.0.1.0.0.dist-info/METADATA
odoo9_addon_account_invoice_pricelist-9.0.1.0.0.dist-info/namespace_packages.txt
